{
  "swagger": "2.0",
  "info": {
    "description": "API for managing users, extracts, and cards.",
    "version": "1.0.0",
    "title": "Node API Project"
  },
  "host": "localhost:3000",
  "basePath": "/api",
  "schemes": [
    "http"
  ],
  "paths": {
    "/users": {
      "get": {
        "summary": "Get all users",
        "responses": {
          "200": {
            "description": "A list of users",
            "schema": {
              "type": "array",
              "items": {
                "$ref": "#/definitions/User"
              }
            }
          }
        }
      },
      "put": {
        "summary": "Update a user",
        "parameters": [
          {
            "name": "user",
            "in": "body",
            "required": true,
            "schema": {
              "$ref": "#/definitions/User"
            }
          }
        ],
        "responses": {
          "200": {
            "description": "User updated successfully"
          }
        }
      },
      "delete": {
        "summary": "Delete a user",
        "parameters": [
          {
            "name": "id",
            "in": "query",
            "required": true,
            "type": "string"
          }
        ],
        "responses": {
          "200": {
            "description": "User deleted successfully"
          }
        }
      }
    }
  },
  "definitions": {
    "User": {
      "type": "object",
      "properties": {
        "id": {
          "type": "string"
        },
        "name": {
          "type": "string"
        },
        "email": {
          "type": "string"
        }
      },
      "required": ["id", "name", "email"]
    }
  }
}